subprocesskiller/LICENSE
subprocesskiller/README.md
subprocesskiller/__init__.py
subprocesskiller/requirements.txt
subprocesskiller/thirdparty.json
subprocesskiller-0.11.dist-info/LICENSE.rst
subprocesskiller-0.11.dist-info/METADATA
subprocesskiller-0.11.dist-info/WHEEL
subprocesskiller-0.11.dist-info/top_level.txt
subprocesskiller-0.11.dist-info/RECORD
