Metadata-Version: 2.1
Name: subprocesskiller
Version: 0.11
Summary: Some functions for killing (sub)processes + children with ctypes - works with shell=True
Home-page: https://github.com/hansalemaos/subprocesskiller
Author: Johannes Fischer
Author-email: aulasparticularesdealemaosp@gmail.com
License: MIT
Keywords: pid,kill,subprocess,children,parents
Classifier: Development Status :: 4 - Beta
Classifier: Programming Language :: Python :: 3 :: Only
Classifier: Programming Language :: Python :: 3.10
Classifier: Topic :: Software Development :: Libraries :: Python Modules
Classifier: Topic :: Utilities
License-File: LICENSE.rst
Requires-Dist: comtypes
Requires-Dist: flatten-any-dict-iterable-or-whatsoever
Requires-Dist: hackyargparser
Requires-Dist: ordered-set
Requires-Dist: subprocess-alive
